classy_blocks/__init__.py
classy_blocks/cbtyping.py
classy_blocks/mesh.py
classy_blocks/assemble/__init__.py
classy_blocks/assemble/assembler.py
classy_blocks/assemble/depot.py
classy_blocks/assemble/dump.py
classy_blocks/assemble/settings.py
classy_blocks/base/__init__.py
classy_blocks/base/element.py
classy_blocks/base/exceptions.py
classy_blocks/base/transforms.py
classy_blocks/construct/__init__.py
classy_blocks/construct/edges.py
classy_blocks/construct/point.py
classy_blocks/construct/series.py
classy_blocks/construct/shape.py
classy_blocks/construct/stack.py
classy_blocks/construct/assemblies/assembly.py
classy_blocks/construct/assemblies/joints.py
classy_blocks/construct/curves/__init__.py
classy_blocks/construct/curves/analytic.py
classy_blocks/construct/curves/curve.py
classy_blocks/construct/curves/discrete.py
classy_blocks/construct/curves/interpolated.py
classy_blocks/construct/curves/interpolators.py
classy_blocks/construct/flat/__init__.py
classy_blocks/construct/flat/face.py
classy_blocks/construct/flat/sketch.py
classy_blocks/construct/flat/sketches/__init__.py
classy_blocks/construct/flat/sketches/annulus.py
classy_blocks/construct/flat/sketches/disk.py
classy_blocks/construct/flat/sketches/grid.py
classy_blocks/construct/flat/sketches/mapped.py
classy_blocks/construct/flat/sketches/spline_round.py
classy_blocks/construct/operations/__init__.py
classy_blocks/construct/operations/box.py
classy_blocks/construct/operations/connector.py
classy_blocks/construct/operations/extrude.py
classy_blocks/construct/operations/loft.py
classy_blocks/construct/operations/operation.py
classy_blocks/construct/operations/revolve.py
classy_blocks/construct/operations/wedge.py
classy_blocks/construct/shapes/__init__.py
classy_blocks/construct/shapes/cylinder.py
classy_blocks/construct/shapes/elbow.py
classy_blocks/construct/shapes/frustum.py
classy_blocks/construct/shapes/rings.py
classy_blocks/construct/shapes/round.py
classy_blocks/construct/shapes/shell.py
classy_blocks-1.9.6.dist-info/licenses/LICENSE
classy_blocks-1.9.6.dist-info/METADATA
classy_blocks-1.9.6.dist-info/WHEEL
classy_blocks-1.9.6.dist-info/top_level.txt
classy_blocks-1.9.6.dist-info/RECORD
