Metadata-Version: 2.4
Name: classy_blocks
Version: 1.9.6
Summary: Python classes for easier creation of openFoam's blockMesh dictionaries.
Author-email: Nejc Jurkovic <kandelabr@gmail.com>
License-Expression: MIT
Project-URL: Homepage, https://github.com/damogranlabs/classy_blocks
Project-URL: Tutorials, https://damogranlabs.com/category/classy_blocks
Project-URL: Bug Tracker, https://github.com/damogranlabs/classy_blocks/issues
Project-URL: Contributing, https://github.com/damogranlabs/classy_blocks/blob/master/CONTRIBUTING.md
Keywords: classy_blocks,OpenFOAM,blockMesh
Requires-Python: >=3.9
License-File: LICENSE
Requires-Dist: numpy
Requires-Dist: scipy
Requires-Dist: nptyping
Requires-Dist: numba
Provides-Extra: dev
Requires-Dist: pytest; extra == "dev"
Requires-Dist: parameterized; extra == "dev"
Requires-Dist: ruff~=0.9; extra == "dev"
Requires-Dist: mypy~=1.2; extra == "dev"
Requires-Dist: pre-commit; extra == "dev"
Dynamic: license-file
